visiongraph_ndi/NDIVideoInput.py
visiongraph_ndi/NDIVideoOutput.py
visiongraph_ndi/__init__.py
visiongraph_ndi-0.2.0.dist-info/licenses/LICENSE
visiongraph_ndi-0.2.0.dist-info/METADATA
visiongraph_ndi-0.2.0.dist-info/WHEEL
visiongraph_ndi-0.2.0.dist-info/top_level.txt
visiongraph_ndi-0.2.0.dist-info/RECORD
