Metadata-Version: 2.4
Name: visiongraph-ndi
Version: 0.2.0
Summary: NDI support for the visiongraph library.
Home-page: https://github.com/cansik/visiongraph-ndi
Author: Florian Bruggisser
Author-email: github@broox.ch
License: MIT License
License-File: LICENSE
Requires-Dist: cyndilib~=0.0.9
Requires-Dist: visiongraph>=1.1.0
Dynamic: author
Dynamic: author-email
Dynamic: description
Dynamic: description-content-type
Dynamic: home-page
Dynamic: license
Dynamic: license-file
Dynamic: requires-dist
Dynamic: summary
